{
  "data": [
    {
      "id": 1,
      "title": "Реализация новой галереи изображений",
      "description": "Реализация нового UI компонента с учетом гайдлайнов дизайн-системы. Детали будут уточнены в процессе разработки.",
      "priority": "Medium",
      "status": "InProgress",
      "assigneeId": 0,
      "assignee": {
        "id": 2,
        "fullName": "Илья Романов",
        "email": "il.romanov@avito.ru",
        "avatarUrl": "https://randomuser.me/api/portraits/men/1.jpg"
      },
      "boardId": 0,
      "boardName": "Редизайн карточки товара"
    },
    {
      "id": 2,
      "title": "Адаптация карточки для мобильных устройств",
      "description": "Адаптация интерфейса для различных разрешений экрана. Детали будут уточнены в процессе разработки.",
      "priority": "Medium",
      "status": "InProgress",
      "assigneeId": 0,
      "assignee": {
        "id": 1,
        "fullName": "Александра Ветрова",
        "email": "al.vetrova@avito.ru",
        "avatarUrl": "https://randomuser.me/api/portraits/women/1.jpg"
      },
      "boardId": 0,
      "boardName": "Редизайн карточки товара"
    },
    {
      "id": 3,
      "title": "Оптимизация загрузки медиа-контента",
      "description": "Оптимизация загрузки и отображения медиа-контента. Детали будут уточнены в процессе разработки.",
      "priority": "Medium",
      "status": "Backlog",
      "assigneeId": 0,
      "assignee": {
        "id": 2,
        "fullName": "Илья Романов",
        "email": "il.romanov@avito.ru",
        "avatarUrl": "https://randomuser.me/api/portraits/men/1.jpg"
      },
      "boardId": 0,
      "boardName": "Редизайн карточки товара"
    },
    {
      "id": 4,
      "title": "Добавление микроанимаций интерфейса",
      "description": "Реализация нового UI компонента с учетом гайдлайнов дизайн-системы. Детали будут уточнены в процессе разработки.",
      "priority": "Low",
      "status": "Backlog",
      "assigneeId": 0,
      "assignee": {
        "id": 1,
        "fullName": "Александра Ветрова",
        "email": "al.vetrova@avito.ru",
        "avatarUrl": "https://randomuser.me/api/portraits/women/1.jpg"
      },
      "boardId": 0,
      "boardName": "Редизайн карточки товара"
    },
    {
      "id": 5,
      "title": "Интеграция с системой рекомендаций",
      "description": "Адаптация интерфейса для различных разрешений экрана. Детали будут уточнены в процессе разработки.",
      "priority": "Medium",
      "status": "Done",
      "assigneeId": 0,
      "assignee": {
        "id": 2,
        "fullName": "Илья Романов",
        "email": "il.romanov@avito.ru",
        "avatarUrl": "https://randomuser.me/api/portraits/men/1.jpg"
      },
      "boardId": 0,
      "boardName": "Редизайн карточки товара"
    },
    {
      "id": 6,
      "title": "Реализация темной темы",
      "description": "Оптимизация загрузки и отображения медиа-контента. Детали будут уточнены в процессе разработки.",
      "priority": "Medium",
      "status": "Backlog",
      "assigneeId": 0,
      "assignee": {
        "id": 1,
        "fullName": "Александра Ветрова",
        "email": "al.vetrova@avito.ru",
        "avatarUrl": "https://randomuser.me/api/portraits/women/1.jpg"
      },
      "boardId": 0,
      "boardName": "Редизайн карточки товара"
    },
    {
      "id": 7,
      "title": "Оптимизация CLS (Cumulative Layout Shift)",
      "description": "Реализация нового UI компонента с учетом гайдлайнов дизайн-системы. Детали будут уточнены в процессе разработки.",
      "priority": "Low",
      "status": "InProgress",
      "assigneeId": 0,
      "assignee": {
        "id": 1,
        "fullName": "Александра Ветрова",
        "email": "al.vetrova@avito.ru",
        "avatarUrl": "https://randomuser.me/api/portraits/women/1.jpg"
      },
      "boardId": 0,
      "boardName": "Редизайн карточки товара"
    },
    {
      "id": 8,
      "title": "Добавление быстрого просмотра товара",
      "description": "Адаптация интерфейса для различных разрешений экрана. Детали будут уточнены в процессе разработки.",
      "priority": "Low",
      "status": "InProgress",
      "assigneeId": 0,
      "assignee": {
        "id": 2,
        "fullName": "Илья Романов",
        "email": "il.romanov@avito.ru",
        "avatarUrl": "https://randomuser.me/api/portraits/men/1.jpg"
      },
      "boardId": 0,
      "boardName": "Редизайн карточки товара"
    },
    {
      "id": 9,
      "title": "Интеграция системы рейтингов",
      "description": "Оптимизация загрузки и отображения медиа-контента. Детали будут уточнены в процессе разработки.",
      "priority": "High",
      "status": "Done",
      "assigneeId": 0,
      "assignee": {
        "id": 2,
        "fullName": "Илья Романов",
        "email": "il.romanov@avito.ru",
        "avatarUrl": "https://randomuser.me/api/portraits/men/1.jpg"
      },
      "boardId": 0,
      "boardName": "Редизайн карточки товара"
    },
    {
      "id": 10,
      "title": "Реализация sticky-панели действий",
      "description": "Реализация нового UI компонента с учетом гайдлайнов дизайн-системы. Детали будут уточнены в процессе разработки.",
      "priority": "Medium",
      "status": "InProgress",
      "assigneeId": 0,
      "assignee": {
        "id": 1,
        "fullName": "Александра Ветрова",
        "email": "al.vetrova@avito.ru",
        "avatarUrl": "https://randomuser.me/api/portraits/women/1.jpg"
      },
      "boardId": 0,
      "boardName": "Редизайн карточки товара"
    },
    {
      "id": 11,
      "title": "Ленивая загрузка изображений",
      "description": "Улучшение показателей Core Web Vitals для страницы. Детали будут уточнены в процессе разработки.",
      "priority": "Low",
      "status": "Done",
      "assigneeId": 0,
      "assignee": {
        "id": 2,
        "fullName": "Илья Романов",
        "email": "il.romanov@avito.ru",
        "avatarUrl": "https://randomuser.me/api/portraits/men/1.jpg"
      },
      "boardId": 0,
      "boardName": "Оптимизация производительности"
    },
    {
      "id": 12,
      "title": "Оптимизация бандла Webpack",
      "description": "Снижение времени загрузки и улучшение отзывчивости интерфейса. Детали будут уточнены в процессе разработки.",
      "priority": "Low",
      "status": "Done",
      "assigneeId": 0,
      "assignee": {
        "id": 2,
        "fullName": "Илья Романов",
        "email": "il.romanov@avito.ru",
        "avatarUrl": "https://randomuser.me/api/portraits/men/1.jpg"
      },
      "boardId": 0,
      "boardName": "Оптимизация производительности"
    },
    {
      "id": 13,
      "title": "Реализация code-splitting",
      "description": "Улучшение показателей Core Web Vitals для страницы. Детали будут уточнены в процессе разработки.",
      "priority": "Medium",
      "status": "InProgress",
      "assigneeId": 0,
      "assignee": {
        "id": 2,
        "fullName": "Илья Романов",
        "email": "il.romanov@avito.ru",
        "avatarUrl": "https://randomuser.me/api/portraits/men/1.jpg"
      },
      "boardId": 0,
      "boardName": "Оптимизация производительности"
    },
    {
      "id": 14,
      "title": "Оптимизация работы с API",
      "description": "Снижение времени загрузки и улучшение отзывчивости интерфейса. Детали будут уточнены в процессе разработки.",
      "priority": "Low",
      "status": "Done",
      "assigneeId": 0,
      "assignee": {
        "id": 2,
        "fullName": "Илья Романов",
        "email": "il.romanov@avito.ru",
        "avatarUrl": "https://randomuser.me/api/portraits/men/1.jpg"
      },
      "boardId": 0,
      "boardName": "Оптимизация производительности"
    },
    {
      "id": 15,
      "title": "Уменьшение времени First Contentful Paint",
      "description": "Улучшение показателей Core Web Vitals для страницы. Детали будут уточнены в процессе разработки.",
      "priority": "High",
      "status": "Done",
      "assigneeId": 0,
      "assignee": {
        "id": 2,
        "fullName": "Илья Романов",
        "email": "il.romanov@avito.ru",
        "avatarUrl": "https://randomuser.me/api/portraits/men/1.jpg"
      },
      "boardId": 0,
      "boardName": "Оптимизация производительности"
    },
    {
      "id": 16,
      "title": "Оптимизация использования памяти",
      "description": "Снижение времени загрузки и улучшение отзывчивости интерфейса. Детали будут уточнены в процессе разработки.",
      "priority": "Medium",
      "status": "Done",
      "assigneeId": 0,
      "assignee": {
        "id": 2,
        "fullName": "Илья Романов",
        "email": "il.romanov@avito.ru",
        "avatarUrl": "https://randomuser.me/api/portraits/men/1.jpg"
      },
      "boardId": 0,
      "boardName": "Оптимизация производительности"
    },
    {
      "id": 17,
      "title": "Устранение jank-анимаций",
      "description": "Улучшение показателей Core Web Vitals для страницы. Детали будут уточнены в процессе разработки.",
      "priority": "High",
      "status": "InProgress",
      "assigneeId": 0,
      "assignee": {
        "id": 1,
        "fullName": "Александра Ветрова",
        "email": "al.vetrova@avito.ru",
        "avatarUrl": "https://randomuser.me/api/portraits/women/1.jpg"
      },
      "boardId": 0,
      "boardName": "Оптимизация производительности"
    },
    {
      "id": 18,
      "title": "Имплементация Virtual Scrolling",
      "description": "Снижение времени загрузки и улучшение отзывчивости интерфейса. Детали будут уточнены в процессе разработки.",
      "priority": "High",
      "status": "Backlog",
      "assigneeId": 0,
      "assignee": {
        "id": 1,
        "fullName": "Александра Ветрова",
        "email": "al.vetrova@avito.ru",
        "avatarUrl": "https://randomuser.me/api/portraits/women/1.jpg"
      },
      "boardId": 0,
      "boardName": "Оптимизация производительности"
    },
    {
      "id": 19,
      "title": "Оптимизация работы с DOM",
      "description": "Улучшение показателей Core Web Vitals для страницы. Детали будут уточнены в процессе разработки.",
      "priority": "Low",
      "status": "Backlog",
      "assigneeId": 0,
      "assignee": {
        "id": 2,
        "fullName": "Илья Романов",
        "email": "il.romanov@avito.ru",
        "avatarUrl": "https://randomuser.me/api/portraits/men/1.jpg"
      },
      "boardId": 0,
      "boardName": "Оптимизация производительности"
    },
    {
      "id": 20,
      "title": "Оптимизация эндпоинта поиска",
      "description": "Улучшение структуры кода и производительности эндпоинта. Детали будут уточнены в процессе разработки.",
      "priority": "Low",
      "status": "InProgress",
      "assigneeId": 0,
      "assignee": {
        "id": 3,
        "fullName": "Дмитрий Козлов",
        "email": "dm.kozlov@avito.ru",
        "avatarUrl": "https://randomuser.me/api/portraits/men/2.jpg"
      },
      "boardId": 0,
      "boardName": "Рефакторинг API"
    },
    {
      "id": 21,
      "title": "Реализация кэширования ответов",
      "description": "Оптимизация запросов к базе данных и кэширования. Детали будут уточнены в процессе разработки.",
      "priority": "Medium",
      "status": "Backlog",
      "assigneeId": 0,
      "assignee": {
        "id": 4,
        "fullName": "Екатерина Смирнова",
        "email": "ek.smirnova@avito.ru",
        "avatarUrl": "https://randomuser.me/api/portraits/women/2.jpg"
      },
      "boardId": 0,
      "boardName": "Рефакторинг API"
    },
    {
      "id": 22,
      "title": "Добавление пагинации в API",
      "description": "Улучшение структуры кода и производительности эндпоинта. Детали будут уточнены в процессе разработки.",
      "priority": "Low",
      "status": "InProgress",
      "assigneeId": 0,
      "assignee": {
        "id": 3,
        "fullName": "Дмитрий Козлов",
        "email": "dm.kozlov@avito.ru",
        "avatarUrl": "https://randomuser.me/api/portraits/men/2.jpg"
      },
      "boardId": 0,
      "boardName": "Рефакторинг API"
    },
    {
      "id": 23,
      "title": "Оптимизация запросов к БД",
      "description": "Оптимизация запросов к базе данных и кэширования. Детали будут уточнены в процессе разработки.",
      "priority": "Medium",
      "status": "Backlog",
      "assigneeId": 0,
      "assignee": {
        "id": 3,
        "fullName": "Дмитрий Козлов",
        "email": "dm.kozlov@avito.ru",
        "avatarUrl": "https://randomuser.me/api/portraits/men/2.jpg"
      },
      "boardId": 0,
      "boardName": "Рефакторинг API"
    },
    {
      "id": 24,
      "title": "Рефакторинг системы авторизации",
      "description": "Улучшение структуры кода и производительности эндпоинта. Детали будут уточнены в процессе разработки.",
      "priority": "Medium",
      "status": "Done",
      "assigneeId": 0,
      "assignee": {
        "id": 4,
        "fullName": "Екатерина Смирнова",
        "email": "ek.smirnova@avito.ru",
        "avatarUrl": "https://randomuser.me/api/portraits/women/2.jpg"
      },
      "boardId": 0,
      "boardName": "Рефакторинг API"
    },
    {
      "id": 25,
      "title": "Добавление rate-limiting",
      "description": "Оптимизация запросов к базе данных и кэширования. Детали будут уточнены в процессе разработки.",
      "priority": "High",
      "status": "Backlog",
      "assigneeId": 0,
      "assignee": {
        "id": 3,
        "fullName": "Дмитрий Козлов",
        "email": "dm.kozlov@avito.ru",
        "avatarUrl": "https://randomuser.me/api/portraits/men/2.jpg"
      },
      "boardId": 0,
      "boardName": "Рефакторинг API"
    },
    {
      "id": 26,
      "title": "Оптимизация сериализации JSON",
      "description": "Улучшение структуры кода и производительности эндпоинта. Детали будут уточнены в процессе разработки.",
      "priority": "High",
      "status": "Backlog",
      "assigneeId": 0,
      "assignee": {
        "id": 4,
        "fullName": "Екатерина Смирнова",
        "email": "ek.smirnova@avito.ru",
        "avatarUrl": "https://randomuser.me/api/portraits/women/2.jpg"
      },
      "boardId": 0,
      "boardName": "Рефакторинг API"
    },
    {
      "id": 27,
      "title": "Реализация bulk-операций",
      "description": "Оптимизация запросов к базе данных и кэширования. Детали будут уточнены в процессе разработки.",
      "priority": "Medium",
      "status": "Done",
      "assigneeId": 0,
      "assignee": {
        "id": 4,
        "fullName": "Екатерина Смирнова",
        "email": "ek.smirnova@avito.ru",
        "avatarUrl": "https://randomuser.me/api/portraits/women/2.jpg"
      },
      "boardId": 0,
      "boardName": "Рефакторинг API"
    },
    {
      "id": 28,
      "title": "Миграция на GraphQL",
      "description": "Улучшение структуры кода и производительности эндпоинта. Детали будут уточнены в процессе разработки.",
      "priority": "Low",
      "status": "Done",
      "assigneeId": 0,
      "assignee": {
        "id": 4,
        "fullName": "Екатерина Смирнова",
        "email": "ek.smirnova@avito.ru",
        "avatarUrl": "https://randomuser.me/api/portraits/women/2.jpg"
      },
      "boardId": 0,
      "boardName": "Рефакторинг API"
    },
    {
      "id": 29,
      "title": "Добавление WebSocket поддержки",
      "description": "Оптимизация запросов к базе данных и кэширования. Детали будут уточнены в процессе разработки.",
      "priority": "Medium",
      "status": "InProgress",
      "assigneeId": 0,
      "assignee": {
        "id": 3,
        "fullName": "Дмитрий Козлов",
        "email": "dm.kozlov@avito.ru",
        "avatarUrl": "https://randomuser.me/api/portraits/men/2.jpg"
      },
      "boardId": 0,
      "boardName": "Рефакторинг API"
    },
    {
      "id": 30,
      "title": "Создание скриптов миграции",
      "description": "Перенос данных с сохранением целостности и консистентности. Детали будут уточнены в процессе разработки.",
      "priority": "Medium",
      "status": "Done",
      "assigneeId": 0,
      "assignee": {
        "id": 4,
        "fullName": "Екатерина Смирнова",
        "email": "ek.smirnova@avito.ru",
        "avatarUrl": "https://randomuser.me/api/portraits/women/2.jpg"
      },
      "boardId": 0,
      "boardName": "Миграция на новую БД"
    },
    {
      "id": 31,
      "title": "Оптимизация индексов",
      "description": "Настройка новой БД для оптимальной производительности. Детали будут уточнены в процессе разработки.",
      "priority": "High",
      "status": "Backlog",
      "assigneeId": 0,
      "assignee": {
        "id": 4,
        "fullName": "Екатерина Смирнова",
        "email": "ek.smirnova@avito.ru",
        "avatarUrl": "https://randomuser.me/api/portraits/women/2.jpg"
      },
      "boardId": 0,
      "boardName": "Миграция на новую БД"
    },
    {
      "id": 32,
      "title": "Настройка репликации",
      "description": "Перенос данных с сохранением целостности и консистентности. Детали будут уточнены в процессе разработки.",
      "priority": "Medium",
      "status": "Backlog",
      "assigneeId": 0,
      "assignee": {
        "id": 3,
        "fullName": "Дмитрий Козлов",
        "email": "dm.kozlov@avito.ru",
        "avatarUrl": "https://randomuser.me/api/portraits/men/2.jpg"
      },
      "boardId": 0,
      "boardName": "Миграция на новую БД"
    },
    {
      "id": 33,
      "title": "Реализация резервного копирования",
      "description": "Настройка новой БД для оптимальной производительности. Детали будут уточнены в процессе разработки.",
      "priority": "Low",
      "status": "Done",
      "assigneeId": 0,
      "assignee": {
        "id": 3,
        "fullName": "Дмитрий Козлов",
        "email": "dm.kozlov@avito.ru",
        "avatarUrl": "https://randomuser.me/api/portraits/men/2.jpg"
      },
      "boardId": 0,
      "boardName": "Миграция на новую БД"
    },
    {
      "id": 34,
      "title": "Профилирование запросов",
      "description": "Перенос данных с сохранением целостности и консистентности. Детали будут уточнены в процессе разработки.",
      "priority": "Low",
      "status": "InProgress",
      "assigneeId": 0,
      "assignee": {
        "id": 4,
        "fullName": "Екатерина Смирнова",
        "email": "ek.smirnova@avito.ru",
        "avatarUrl": "https://randomuser.me/api/portraits/women/2.jpg"
      },
      "boardId": 0,
      "boardName": "Миграция на новую БД"
    },
    {
      "id": 35,
      "title": "Настройка connection pooling",
      "description": "Настройка новой БД для оптимальной производительности. Детали будут уточнены в процессе разработки.",
      "priority": "Low",
      "status": "Backlog",
      "assigneeId": 0,
      "assignee": {
        "id": 3,
        "fullName": "Дмитрий Козлов",
        "email": "dm.kozlov@avito.ru",
        "avatarUrl": "https://randomuser.me/api/portraits/men/2.jpg"
      },
      "boardId": 0,
      "boardName": "Миграция на новую БД"
    },
    {
      "id": 36,
      "title": "Миграция данных",
      "description": "Перенос данных с сохранением целостности и консистентности. Детали будут уточнены в процессе разработки.",
      "priority": "Low",
      "status": "Backlog",
      "assigneeId": 0,
      "assignee": {
        "id": 4,
        "fullName": "Екатерина Смирнова",
        "email": "ek.smirnova@avito.ru",
        "avatarUrl": "https://randomuser.me/api/portraits/women/2.jpg"
      },
      "boardId": 0,
      "boardName": "Миграция на новую БД"
    },
    {
      "id": 37,
      "title": "Написание E2E тестов для основного флоу",
      "description": "Создание автоматических тестов для критического функционала. Детали будут уточнены в процессе разработки.",
      "priority": "High",
      "status": "Backlog",
      "assigneeId": 0,
      "assignee": {
        "id": 5,
        "fullName": "Артем Белов",
        "email": "ar.belov@avito.ru",
        "avatarUrl": "https://randomuser.me/api/portraits/men/3.jpg"
      },
      "boardId": 0,
      "boardName": "Автоматизация тестирования"
    },
    {
      "id": 38,
      "title": "Интеграция с CI/CD",
      "description": "Интеграция тестов в процесс разработки. Детали будут уточнены в процессе разработки.",
      "priority": "Medium",
      "status": "InProgress",
      "assigneeId": 0,
      "assignee": {
        "id": 5,
        "fullName": "Артем Белов",
        "email": "ar.belov@avito.ru",
        "avatarUrl": "https://randomuser.me/api/portraits/men/3.jpg"
      },
      "boardId": 0,
      "boardName": "Автоматизация тестирования"
    },
    {
      "id": 39,
      "title": "Реализация тестов API",
      "description": "Создание автоматических тестов для критического функционала. Детали будут уточнены в процессе разработки.",
      "priority": "Low",
      "status": "Done",
      "assigneeId": 0,
      "assignee": {
        "id": 6,
        "fullName": "Ольга Новикова",
        "email": "ol.novikova@avito.ru",
        "avatarUrl": "https://randomuser.me/api/portraits/women/3.jpg"
      },
      "boardId": 0,
      "boardName": "Автоматизация тестирования"
    },
    {
      "id": 40,
      "title": "Создание тестов производительности",
      "description": "Интеграция тестов в процесс разработки. Детали будут уточнены в процессе разработки.",
      "priority": "Low",
      "status": "Backlog",
      "assigneeId": 0,
      "assignee": {
        "id": 5,
        "fullName": "Артем Белов",
        "email": "ar.belov@avito.ru",
        "avatarUrl": "https://randomuser.me/api/portraits/men/3.jpg"
      },
      "boardId": 0,
      "boardName": "Автоматизация тестирования"
    },
    {
      "id": 41,
      "title": "Настройка алертов для тестов",
      "description": "Создание автоматических тестов для критического функционала. Детали будут уточнены в процессе разработки.",
      "priority": "High",
      "status": "Backlog",
      "assigneeId": 0,
      "assignee": {
        "id": 6,
        "fullName": "Ольга Новикова",
        "email": "ol.novikova@avito.ru",
        "avatarUrl": "https://randomuser.me/api/portraits/women/3.jpg"
      },
      "boardId": 0,
      "boardName": "Автоматизация тестирования"
    },
    {
      "id": 42,
      "title": "Интеграция с Allure отчетностью",
      "description": "Интеграция тестов в процесс разработки. Детали будут уточнены в процессе разработки.",
      "priority": "Low",
      "status": "Done",
      "assigneeId": 0,
      "assignee": {
        "id": 5,
        "fullName": "Артем Белов",
        "email": "ar.belov@avito.ru",
        "avatarUrl": "https://randomuser.me/api/portraits/men/3.jpg"
      },
      "boardId": 0,
      "boardName": "Автоматизация тестирования"
    },
    {
      "id": 43,
      "title": "Тестирование на разных устройствах",
      "description": "Создание автоматических тестов для критического функционала. Детали будут уточнены в процессе разработки.",
      "priority": "Low",
      "status": "Done",
      "assigneeId": 0,
      "assignee": {
        "id": 5,
        "fullName": "Артем Белов",
        "email": "ar.belov@avito.ru",
        "avatarUrl": "https://randomuser.me/api/portraits/men/3.jpg"
      },
      "boardId": 0,
      "boardName": "Автоматизация тестирования"
    },
    {
      "id": 44,
      "title": "Реализация тестов безопасности",
      "description": "Интеграция тестов в процесс разработки. Детали будут уточнены в процессе разработки.",
      "priority": "Medium",
      "status": "Backlog",
      "assigneeId": 0,
      "assignee": {
        "id": 6,
        "fullName": "Ольга Новикова",
        "email": "ol.novikova@avito.ru",
        "avatarUrl": "https://randomuser.me/api/portraits/women/3.jpg"
      },
      "boardId": 0,
      "boardName": "Автоматизация тестирования"
    },
    {
      "id": 45,
      "title": "Настройка кластера Kubernetes",
      "description": "Миграция сервисов с сохранением отказоустойчивости. Детали будут уточнены в процессе разработки.",
      "priority": "Medium",
      "status": "Backlog",
      "assigneeId": 0,
      "assignee": {
        "id": 7,
        "fullName": "Максим Орлов",
        "email": "mx.orlov@avito.ru",
        "avatarUrl": "https://randomuser.me/api/portraits/men/4.jpg"
      },
      "boardId": 0,
      "boardName": "Переход на Kubernetes"
    },
    {
      "id": 46,
      "title": "Реализация Helm-чартов",
      "description": "Настройка оркестрации для эффективного управления ресурсами. Детали будут уточнены в процессе разработки.",
      "priority": "High",
      "status": "InProgress",
      "assigneeId": 0,
      "assignee": {
        "id": 7,
        "fullName": "Максим Орлов",
        "email": "mx.orlov@avito.ru",
        "avatarUrl": "https://randomuser.me/api/portraits/men/4.jpg"
      },
      "boardId": 0,
      "boardName": "Переход на Kubernetes"
    },
    {
      "id": 47,
      "title": "Настройка мониторинга",
      "description": "Миграция сервисов с сохранением отказоустойчивости. Детали будут уточнены в процессе разработки.",
      "priority": "Medium",
      "status": "Backlog",
      "assigneeId": 0,
      "assignee": {
        "id": 7,
        "fullName": "Максим Орлов",
        "email": "mx.orlov@avito.ru",
        "avatarUrl": "https://randomuser.me/api/portraits/men/4.jpg"
      },
      "boardId": 0,
      "boardName": "Переход на Kubernetes"
    },
    {
      "id": 48,
      "title": "Конфигурация ingress-контроллеров",
      "description": "Настройка оркестрации для эффективного управления ресурсами. Детали будут уточнены в процессе разработки.",
      "priority": "Low",
      "status": "InProgress",
      "assigneeId": 0,
      "assignee": {
        "id": 7,
        "fullName": "Максим Орлов",
        "email": "mx.orlov@avito.ru",
        "avatarUrl": "https://randomuser.me/api/portraits/men/4.jpg"
      },
      "boardId": 0,
      "boardName": "Переход на Kubernetes"
    },
    {
      "id": 49,
      "title": "Автоматизация деплоя",
      "description": "Миграция сервисов с сохранением отказоустойчивости. Детали будут уточнены в процессе разработки.",
      "priority": "High",
      "status": "InProgress",
      "assigneeId": 0,
      "assignee": {
        "id": 7,
        "fullName": "Максим Орлов",
        "email": "mx.orlov@avito.ru",
        "avatarUrl": "https://randomuser.me/api/portraits/men/4.jpg"
      },
      "boardId": 0,
      "boardName": "Переход на Kubernetes"
    },
    {
      "id": 50,
      "title": "Настройка auto-scaling",
      "description": "Настройка оркестрации для эффективного управления ресурсами. Детали будут уточнены в процессе разработки.",
      "priority": "Low",
      "status": "Done",
      "assigneeId": 0,
      "assignee": {
        "id": 7,
        "fullName": "Максим Орлов",
        "email": "mx.orlov@avito.ru",
        "avatarUrl": "https://randomuser.me/api/portraits/men/4.jpg"
      },
      "boardId": 0,
      "boardName": "Переход на Kubernetes"
    },
    {
      "id": 51,
      "title": "Миграция stateful-сервисов",
      "description": "Миграция сервисов с сохранением отказоустойчивости. Детали будут уточнены в процессе разработки.",
      "priority": "Medium",
      "status": "Backlog",
      "assigneeId": 0,
      "assignee": {
        "id": 7,
        "fullName": "Максим Орлов",
        "email": "mx.orlov@avito.ru",
        "avatarUrl": "https://randomuser.me/api/portraits/men/4.jpg"
      },
      "boardId": 0,
      "boardName": "Переход на Kubernetes"
    }
  ]
}